[
  { "desc": "Spiaggia con rocce", "id": 12 },
  { "desc": "Tramonto con alberi", "id": 83 },
  { "desc": "Gocce di rugiada su superfice nera", "id": 115 },
  { "desc": "Giaguaro su strada sterrata", "id": 219 },
  { "desc": "Vicolo con case vecchie", "id": 369 },
  { "desc": "Chicchi di caffe sul tavolo", "id": 425 },
  { "desc": "Tazzina bianca con lamponi", "id": 429 },
  { "desc": "Macchina da scrivere", "id": 486 },
  { "desc": "Frafole e muesli", "id": 493 },
  { "desc": "Jeep davanti una casa", "id": 514 },
  { "desc": "Montagne innevate", "id": 908 }
]
